cursorcraft/__init__.py
cursorcraft/cli.py
cursorcraft-0.1.1.dist-info/METADATA
cursorcraft-0.1.1.dist-info/WHEEL
cursorcraft-0.1.1.dist-info/entry_points.txt
cursorcraft-0.1.1.dist-info/RECORD
