Metadata-Version: 2.3
Name: cursorcraft
Version: 0.1.1
Summary: Auto-install & update Cursor IDE with desktop integration and notifications
License: MIT
Keywords: cursor,appimage,auto-update,cli
Author: Muhammad Sadiq Ajmal
Author-email: sadiqajmal56@gmail.com
Requires-Python: >=3.7
Classifier: License :: OSI Approved :: MIT License
Classifier: Programming Language :: Python :: 3
Classifier: Programming Language :: Python :: 3.7
Classifier: Programming Language :: Python :: 3.8
Classifier: Programming Language :: Python :: 3.9
Classifier: Programming Language :: Python :: 3.10
Classifier: Programming Language :: Python :: 3.11
Classifier: Programming Language :: Python :: 3.12
Classifier: Programming Language :: Python :: 3.13
Requires-Dist: click (>=8.1,<9.0)
Requires-Dist: python-crontab (>=2.5,<3.0)
Requires-Dist: requests (>=2.28,<3.0)
Requires-Dist: tqdm (>=4.65,<5.0)
Project-URL: Homepage, https://github.com/sussadiq/cursorcraft
Project-URL: Repository, https://github.com/sussadiq/cursorcraft
